img/output_of_multiple_well_known_unix_commands_2023-12-28T19_13_32_605621.svg
img/output_of_multiple_well_known_unix_commands_2023-12-28T19_13_40_503695.svg
img/summary_2023-12-28T19_05_20_213933.svg
img/summary_2023-12-28T19_05_44_404837.svg
img/summary_2023-12-28T19_05_55_822030.svg
kodegeek_textualize/__init__.py
kodegeek_textualize/competitors_app.tcss
kodegeek_textualize/details_screen.tcss
kodegeek_textualize/log_screen.tcss
kodegeek_textualize/log_scroller.py
kodegeek_textualize/os_app.tcss
kodegeek_textualize/table_with_detail_screen.py
KodegeekTextualize-0.0.5.dist-info/LICENSE
KodegeekTextualize-0.0.5.dist-info/METADATA
KodegeekTextualize-0.0.5.dist-info/WHEEL
KodegeekTextualize-0.0.5.dist-info/entry_points.txt
KodegeekTextualize-0.0.5.dist-info/top_level.txt
KodegeekTextualize-0.0.5.dist-info/RECORD
