Metadata-Version: 2.1
Name: KodegeekTextualize
Version: 0.0.5
Summary: Collection of scripts that show how to use several features of textualize
Author-email: Jose Vicente Nunez <kodegeek.com@protonmail.com>
Keywords: running,race
Classifier: Environment :: Console
Classifier: Development Status :: 4 - Beta
Classifier: Programming Language :: Python :: 3
Classifier: Intended Audience :: End Users/Desktop
Classifier: Topic :: Utilities
Requires-Python: >=3.9
License-File: LICENSE
Requires-Dist: textual-dev ==1.3.0
Requires-Dist: textual ~=0.46.0
Requires-Dist: rich ==13.6.0
